kvdr/__init__.py
kvdr/dump.py
kvdr/kvdr.py
kvdr/load.py
kvdr/util.py
kvdr/version.py
kvdr-1.0.4.dist-info/LICENSE
kvdr-1.0.4.dist-info/METADATA
kvdr-1.0.4.dist-info/WHEEL
kvdr-1.0.4.dist-info/entry_points.txt
kvdr-1.0.4.dist-info/top_level.txt
kvdr-1.0.4.dist-info/RECORD
