Metadata-Version: 2.1
Name: kvdr
Version: 1.0.4
Summary: KVDR - Key/Value Dump and Restore
Home-page: https://gitlab.com/dejan/kvdr
Author: Dejan Lekic
Author-email: dejan.lekic@gmail.com
License: BSD 3-Clause License
Download-URL: https://gitlab.com/dejan/kvdr
Project-URL: Documentation, https://gitlab.com/dejan/kvdr
Project-URL: Code, https://gitlab.com/dejan/kvdr
Project-URL: Issue tracker, https://gitlab.com/dejan/kvdr/issues
Platform: UNKNOWN
Classifier: Programming Language :: Python :: 3
Classifier: License :: OSI Approved :: BSD License
Classifier: Operating System :: OS Independent
Classifier: Development Status :: 5 - Production/Stable
Classifier: Environment :: Console
Classifier: Intended Audience :: System Administrators
Classifier: Topic :: System :: Recovery Tools
Requires-Python: >=3.0
Requires-Dist: redis (>=3.0.0)
Requires-Dist: docopt (>=0.6.0)
